streamlit_image_composite/__init__.py
streamlit_image_composite/frontend/build/asset-manifest.json
streamlit_image_composite/frontend/build/bootstrap.min.css
streamlit_image_composite/frontend/build/index.html
streamlit_image_composite/frontend/build/precache-manifest.e26c8a5d8c86450ed3c0f1eedb1cdb51.js
streamlit_image_composite/frontend/build/service-worker.js
streamlit_image_composite/frontend/build/assets/elon_musk.png
streamlit_image_composite/frontend/build/assets/padang_padang.jpeg
streamlit_image_composite/frontend/build/static/js/2.c828c0d3.chunk.js
streamlit_image_composite/frontend/build/static/js/2.c828c0d3.chunk.js.LICENSE.txt
streamlit_image_composite/frontend/build/static/js/2.c828c0d3.chunk.js.map
streamlit_image_composite/frontend/build/static/js/main.4d37834d.chunk.js
streamlit_image_composite/frontend/build/static/js/main.4d37834d.chunk.js.map
streamlit_image_composite/frontend/build/static/js/runtime-main.44d30fc2.js
streamlit_image_composite/frontend/build/static/js/runtime-main.44d30fc2.js.map
streamlit_image_composite-0.0.9.dist-info/LICENSE
streamlit_image_composite-0.0.9.dist-info/METADATA
streamlit_image_composite-0.0.9.dist-info/WHEEL
streamlit_image_composite-0.0.9.dist-info/top_level.txt
streamlit_image_composite-0.0.9.dist-info/RECORD
